{"stats":{"minecraft:used":{"minecraft:cooked_mutton":1,"minecraft:stone_pickaxe":245,"minecraft:oak_planks":1,"minecraft:shield":103,"minecraft:cooked_salmon":7,"minecraft:crafting_table":4,"minecraft:black_wool":3,"minecraft:gravel":2,"minecraft:stone_axe":211,"minecraft:cobblestone":53,"minecraft:bow":8,"minecraft:furnace":5,"minecraft:cooked_porkchop":1,"minecraft:andesite":1},"minecraft:dropped":{"minecraft:furnace":4,"minecraft:oak_log":24,"minecraft:salmon":97,"minecraft:coal":25,"minecraft:shield":1},"minecraft:custom":{"minecraft:interact_with_furnace":20,"minecraft:mob_kills":166,"minecraft:interact_with_crafting_table":7,"minecraft:leave_game":3,"minecraft:time_since_death":104628,"minecraft:climb_one_cm":44,"minecraft:time_since_rest":104628,"minecraft:sprint_one_cm":185162,"minecraft:damage_taken":385,"minecraft:walk_one_cm":139174,"minecraft:damage_blocked_by_shield":2290,"minecraft:drop":10,"minecraft:damage_dealt":15109,"minecraft:swim_one_cm":191384,"minecraft:fly_one_cm":37427,"minecraft:open_chest":3,"minecraft:crouch_one_cm":4104,"minecraft:play_time":104628,"minecraft:sneak_time":3329,"minecraft:walk_under_water_one_cm":50174,"minecraft:jump":989,"minecraft:walk_on_water_one_cm":22482,"minecraft:total_world_time":104628,"minecraft:fall_one_cm":4270},"minecraft:broken":{"minecraft:stone_pickaxe":2,"minecraft:stone_axe":3},"minecraft:crafted":{"minecraft:oak_planks":28,"minecraft:cooked_porkchop":1,"minecraft:crafting_table":1,"minecraft:furnace":4,"minecraft:stone_axe":3,"minecraft:cooked_mutton":1,"minecraft:shield":2,"minecraft:stick":24,"minecraft:iron_ingot":4,"minecraft:stone_pickaxe":1},"minecraft:picked_up":{"minecraft:crafting_table":3,"minecraft:salmon":97,"minecraft:andesite":1,"minecraft:flint":3,"minecraft:oak_log":31,"minecraft:gunpowder":3,"minecraft:lapis_lazuli":23,"minecraft:dirt":1,"minecraft:string":10,"minecraft:bone":13,"minecraft:bow":1,"minecraft:iron_ingot":2,"minecraft:stone_pickaxe":1,"minecraft:oak_planks":1,"minecraft:furnace":5,"minecraft:raw_iron":41,"minecraft:gravel":2,"minecraft:porkchop":1,"minecraft:spider_eye":4,"minecraft:arrow":12,"minecraft:rotten_flesh":13,"minecraft:bone_meal":2,"minecraft:black_wool":4,"minecraft:mutton":1,"minecraft:coal":91,"minecraft:cobblestone":100},"minecraft:mined":{"minecraft:crafting_table":3,"minecraft:lapis_ore":2,"minecraft:furnace":5,"minecraft:iron_ore":41,"minecraft:andesite":1,"minecraft:black_wool":3,"minecraft:grass":1,"minecraft:oak_log":32,"minecraft:coal_ore":87,"minecraft:gravel":5,"minecraft:dirt":1,"minecraft:stone":86},"minecraft:killed":{"minecraft:pig":1,"minecraft:salmon":99,"minecraft:spider":9,"minecraft:bat":1,"minecraft:creeper":6,"minecraft:sheep":1,"minecraft:skeleton":25,"minecraft:zombie":14,"minecraft:drowned":7}},"DataVersion":3465}